bm25_search.cpython-38-i386-linux-gnu.so
bm25_search.libs/libgcc_s-1257a076.so.1
bm25_search.libs/libstdc++-0530927c.so.6.0.32
bm25_search-0.2.0.dist-info/LICENSE
bm25_search-0.2.0.dist-info/WHEEL
bm25_search-0.2.0.dist-info/METADATA
bm25_search-0.2.0.dist-info/top_level.txt
bm25_search-0.2.0.dist-info/RECORD
