Metadata-Version: 2.1
Name: bm25-search
Version: 0.2.0
Summary: Python Package with BM25 Algorithms C++ extension using Pybind11
Home-page: UNKNOWN
License: UNKNOWN
Platform: UNKNOWN
License-File: LICENSE
